soneda/__init__.py
soneda/__main__.py
soneda/cli.py
soneda/logging.conf
soneda/logging_conf.py
soneda/py.typed
soneda/twitter/app.py
soneda/twitter/client.py
soneda/twitter/exceptions.py
soneda-0.0.0.dist-info/entry_points.txt
soneda-0.0.0.dist-info/LICENSE
soneda-0.0.0.dist-info/WHEEL
soneda-0.0.0.dist-info/METADATA
soneda-0.0.0.dist-info/RECORD
