Metadata-Version: 2.1
Name: soneda
Version: 0.0.0
Summary: Social Networks Data Analytics
Home-page: https://github.com/eLearningHub/SoNeDa
License: MIT
Author: Behzad Samadi
Author-email: behzad@mechatronics3d.com
Requires-Python: >=3.7,<4.0
Classifier: Development Status :: 1 - Planning
Classifier: License :: OSI Approved :: MIT License
Classifier: Programming Language :: Python :: 3
Classifier: Programming Language :: Python :: 3.10
Classifier: Programming Language :: Python :: 3.7
Classifier: Programming Language :: Python :: 3.8
Classifier: Programming Language :: Python :: 3.9
Requires-Dist: click (>=8.0.1)
Project-URL: Changelog, https://github.com/eLearningHub/SoNeDa/releases
Project-URL: Documentation, https://soneda.readthedocs.io
Project-URL: Repository, https://github.com/eLearningHub/SoNeDa
